dash_access_manager/__init__.py
dash_access_manager/login.py
dash_access_manager/logout.py
dash_access_manager/models.py
dash_access_manager/signup.py
dash_access_manager-0.1.3.dist-info/LICENSE
dash_access_manager-0.1.3.dist-info/METADATA
dash_access_manager-0.1.3.dist-info/WHEEL
dash_access_manager-0.1.3.dist-info/top_level.txt
dash_access_manager-0.1.3.dist-info/RECORD
