Metadata-Version: 2.1
Name: dash-access-manager
Version: 0.1.3
Summary: Dash-Access-Manager provides user access management for Dash.
Home-page: https://github.com/evan-lh/dash-access-manager
Author: Evan
Author-email: elehella@enssat.fr
License: MIT
Platform: UNKNOWN
Requires-Dist: bcrypt
Requires-Dist: mongoengine
Requires-Dist: flask-login
Requires-Dist: dnspython
Requires-Dist: dash
Requires-Dist: dash-bootstrap-components
